data_cleaner_bonc/__init__.py
data_cleaner_bonc/cleaner_util.py
data_cleaner_bonc/es_cleaner.py
data_cleaner_bonc/mysql_cleaner.py
data_cleaner_bonc-0.0.1.dist-info/METADATA
data_cleaner_bonc-0.0.1.dist-info/WHEEL
data_cleaner_bonc-0.0.1.dist-info/top_level.txt
data_cleaner_bonc-0.0.1.dist-info/zip-safe
data_cleaner_bonc-0.0.1.dist-info/RECORD
