Metadata-Version: 2.1
Name: data_cleaner_bonc
Version: 0.0.1
Summary: 基标讯清理工具包工具包
Requires-Dist: elasticsearch==8.17.2
Requires-Dist: regex==2024.9.11
Requires-Dist: pymysql~=1.0.2
